setup.py
Gauss_Binomial_Distribution/Binomialdistribution.py
Gauss_Binomial_Distribution/Gaussiandistribution.py
Gauss_Binomial_Distribution/Generaldistribution.py
Gauss_Binomial_Distribution/__init__.py
Gauss_Binomial_Distributions.egg-info/PKG-INFO
Gauss_Binomial_Distributions.egg-info/SOURCES.txt
Gauss_Binomial_Distributions.egg-info/dependency_links.txt
Gauss_Binomial_Distributions.egg-info/not-zip-safe
Gauss_Binomial_Distributions.egg-info/top_level.txt