Metadata-Version: 1.0
Name: Gauss-Binomial-Distributions
Version: 0.101
Summary: Gaussian and Binomial distributions
Home-page: UNKNOWN
Author: Adebowale Daniel
Author-email: negeek5ive@gmail.com
License: UNKNOWN
Platform: UNKNOWN
